<?xml version="1.0" encoding="UTF-8"?>
<!DOCTYPE hibernate-mapping PUBLIC 
	"-//Hibernate/Hibernate Mapping DTD 3.0//EN"
	"http://hibernate.sourceforge.net/hibernate-mapping-3.0.dtd">
<hibernate-mapping package="org.noka.item">
<class name="DlForRoleItem" table="NK_SYS_DLFORROLE">
<id name="drid">
	<generator class="increment"/>
</id>
<property name="droleid"  />
<property name="drtablename" />
<property name="druserfield"/>
<property name="drdeptfield"/>
<property name="drtype"/>
<property name="drdept"/>
</class>
</hibernate-mapping>
